Metadata-Version: 2.1
Name: xbot.framework
Version: 0.4.0
Summary: A lightweight, easy-to-use, and extensible automation testing framework.
Home-page: https://github.com/zhaowcheng/xbot.framework
Author: zhaowcheng
Author-email: zhaowcheng@163.com
License: UNKNOWN
Project-URL: Homepage, https://github.com/zhaowcheng/xbot.framework
Project-URL: Issues, https://github.com/zhaowcheng/xbot.framework/issues
Platform: UNKNOWN
Classifier: License :: OSI Approved :: BSD License
Classifier: Operating System :: OS Independent
Classifier: Programming Language :: Python :: 3
Classifier: Programming Language :: Python :: 3.6
Classifier: Programming Language :: Python :: 3.7
Classifier: Programming Language :: Python :: 3.8
Classifier: Programming Language :: Python :: 3.9
Classifier: Programming Language :: Python :: 3.10
Classifier: Programming Language :: Python :: 3.11
Classifier: Programming Language :: Python :: 3.12
Requires-Python: >=3.6
License-File: LICENSE
Requires-Dist: jinja2 ; python_version >= "3.6"
Requires-Dist: ruamel.yaml ; python_version >= "3.6"
Requires-Dist: jmespath ; python_version >= "3.6"
